nicou11_cmd/__init__.py
nicou11_cmd/cmd.py
nicou11_cmd-0.1.1.dist-info/METADATA
nicou11_cmd-0.1.1.dist-info/WHEEL
nicou11_cmd-0.1.1.dist-info/entry_points.txt
nicou11_cmd-0.1.1.dist-info/top_level.txt
nicou11_cmd-0.1.1.dist-info/RECORD
