Metadata-Version: 2.1
Name: nicou11_cmd
Version: 0.1.1
Summary: Default template for PDM package
Author-email: Nicou11 <lyoungin1204@gmail.com>
License: MIT
Requires-Python: >=3.9
Requires-Dist: nicou11-lotto >=0.2.0
